typedconfig_awssource/__init__.py
typedconfig_awssource/__version__.py
typedconfig_awssource/config_source.py
typed_config_aws_sources-0.4.2.dist-info/LICENSE
typed_config_aws_sources-0.4.2.dist-info/METADATA
typed_config_aws_sources-0.4.2.dist-info/WHEEL
typed_config_aws_sources-0.4.2.dist-info/top_level.txt
typed_config_aws_sources-0.4.2.dist-info/RECORD
