Metadata-Version: 2.1
Name: typed-config-aws-sources
Version: 0.4.2
Summary: AWS config sources for the typedconfig package
Home-page: https://github.com/bwindsor/typed-config-aws-sources
Author: Ben Windsor
Author-email: 
License: MIT
Platform: UNKNOWN
Classifier: Programming Language :: Python :: 3
Classifier: Programming Language :: Python :: 3.6
Classifier: Programming Language :: Python :: 3.7
Classifier: Development Status :: 4 - Beta
Classifier: Intended Audience :: Developers
Classifier: License :: OSI Approved :: MIT License
Classifier: Topic :: Software Development
Classifier: Typing :: Typed
Requires-Python: >=3.6.0
Requires-Dist: boto3
Requires-Dist: typed-config
